{"forsen5G": {"likely emotion": "rivalry", "times tested": [1, 1, 1, 1], "pleasentness": 0, "attention": 0, "sensitivity": 0, "aptitude": 0}, "homyLol": {"likely emotion": "rivalry", "times tested": [1, 1, 1, 1], "pleasentness": 0, "attention": 0, "sensitivity": 0, "aptitude": 0}, "chipsaKEK": {"likely emotion": "rivalry", "times tested": [1, 1, 1, 1], "pleasentness": 0, "attention": 0, "sensitivity": 0, "aptitude": 0}, "TriHard": {"likely emotion": "frivolity", "times tested": [63, 65, 83, 73], "pleasentness": 56.56, "attention": -53.06, "sensitivity": 5.4, "aptitude": 1.44}, "R)": {"likely emotion": "frustation", "times tested": [3, 10, 4, 4], "pleasentness": -0.06, "attention": 2.84, "sensitivity": 0.03, "aptitude": 1.03}, "LUL": {"likely emotion": "gloat", "times tested": [517, 447, 456, 491], "pleasentness": 174.88, "attention": 118.37, "sensitivity": 14.1, "aptitude": -146.27}, "forsenSven": {"likely emotion": "submission", "times tested": [9, 5, 5, 9], "pleasentness": 1.5, "attention": -2.77, "sensitivity": -1.81, "aptitude": 5.06}, "forsen5DVD": {"likely emotion": "rivalry", "times tested": [1, 1, 1, 1], "pleasentness": 0, "attention": 0, "sensitivity": 0, "aptitude": 0}, "forsenBoys": {"likely emotion": "remorse", "times tested": [9, 11, 6, 10], "pleasentness": -0.77, "attention": -0.98, "sensitivity": -0.5, "aptitude": -3.73}, "suwieOwO": {"likely emotion": "rivalry", "times tested": [1, 1, 1, 1], "pleasentness": 0, "attention": 0, "sensitivity": 0, "aptitude": 0}, "forsenE": {"likely emotion": "love", "times tested": [101, 71, 79, 100], "pleasentness": 28.41, "attention": 3.03, "sensitivity": -16.49, "aptitude": 16.13}, "empiSwag": {"likely emotion": "contempt", "times tested": [1, 1, 1, 2], "pleasentness": 0, "attention": 0, "sensitivity": 0, "aptitude": -0.39}, "Kappa": {"likely emotion": "frivolity", "times tested": [267, 290, 270, 309], "pleasentness": 111.92, "attention": -123.46, "sensitivity": -12.76, "aptitude": 19.05}, "&lt;3": {"likely emotion": "rivalry", "times tested": [1, 1, 1, 1], "pleasentness": 0, "attention": 0, "sensitivity": 0, "aptitude": 0}, "xqcL": {"likely emotion": "love", "times tested": [228, 245, 240, 250], "pleasentness": 113.43, "attention": -1.73, "sensitivity": -0.9, "aptitude": 119.79}, "chipsaYil": {"likely emotion": "frivolity", "times tested": [3, 3, 3, 2], "pleasentness": 0.21, "attention": -0.64, "sensitivity": -0.1, "aptitude": 0.23}, "PogChamp": {"likely emotion": "awe", "times tested": [130, 134, 122, 129], "pleasentness": 27.38, "attention": -62.06, "sensitivity": -47.13, "aptitude": -3.25}, "B)": {"likely emotion": "frustation", "times tested": [7, 5, 6, 9], "pleasentness": -2.0, "attention": 0.92, "sensitivity": -1.84, "aptitude": -0.35}, "moon2E": {"likely emotion": "rivalry", "times tested": [1, 1, 1, 1], "pleasentness": 0, "attention": 0, "sensitivity": 0, "aptitude": 0}, "BibleThump": {"likely emotion": "remorse", "times tested": [160, 239, 144, 217], "pleasentness": -83.84, "attention": -80.55, "sensitivity": -26.36, "aptitude": -114.16}, "dcoytv12345": {"likely emotion": "rivalry", "times tested": [1, 1, 1, 1], "pleasentness": 0, "attention": 0, "sensitivity": 0, "aptitude": 0}, "SMOrc": {"likely emotion": "aggressiveness", "times tested": [46, 45, 51, 37], "pleasentness": -9.45, "attention": 22.97, "sensitivity": 31.96, "aptitude": 7.18}, "CorgiDerp": {"likely emotion": "love", "times tested": [3, 1, 2, 4], "pleasentness": 0.43, "attention": 0, "sensitivity": -0.2, "aptitude": 0.14}, "HungryPaimon": {"likely emotion": "awe", "times tested": [5, 8, 6, 8], "pleasentness": 0.28, "attention": -0.89, "sensitivity": -0.89, "aptitude": 0.85}, "forsenPls": {"likely emotion": "frivolity", "times tested": [59, 58, 65, 56], "pleasentness": 42.92, "attention": -1.04, "sensitivity": 5.8, "aptitude": -0.53}, "cmonBruh": {"likely emotion": "disapproval", "times tested": [62, 67, 59, 59], "pleasentness": -48.61, "attention": -55.98, "sensitivity": 26.02, "aptitude": -25.57}, ":)": {"likely emotion": "rivalry", "times tested": [64, 45, 55, 65], "pleasentness": 8.27, "attention": -2.23, "sensitivity": 22.3, "aptitude": 13.05}, "markzYnk": {"likely emotion": "rivalry", "times tested": [1, 1, 1, 1], "pleasentness": 0, "attention": 0, "sensitivity": 0, "aptitude": 0}, "papaL": {"likely emotion": "rivalry", "times tested": [1, 1, 1, 1], "pleasentness": 0, "attention": 0, "sensitivity": 0, "aptitude": 0}, "NotLikeThis": {"likely emotion": "frustation", "times tested": [226, 182, 154, 182], "pleasentness": -50.96, "attention": 69.1, "sensitivity": 2.38, "aptitude": -45.87}, ":D": {"likely emotion": "frivolity", "times tested": [31, 21, 17, 21], "pleasentness": 7.99, "attention": -6.52, "sensitivity": 3.32, "aptitude": -2.79}, "yyjSmile": {"likely emotion": "envy", "times tested": [2, 1, 1, 2], "pleasentness": -0.38, "attention": 0, "sensitivity": 0, "aptitude": 0.85}, "pcrowDoodle": {"likely emotion": "rivalry", "times tested": [1, 1, 1, 1], "pleasentness": 0, "attention": 0, "sensitivity": 0, "aptitude": 0}, "pokiW": {"likely emotion": "contempt", "times tested": [1, 2, 2, 4], "pleasentness": 0, "attention": 0.26, "sensitivity": 0.33, "aptitude": -1.01}, "shiftBeter": {"likely emotion": "rivalry", "times tested": [1, 1, 1, 1], "pleasentness": 0, "attention": 0, "sensitivity": 0, "aptitude": 0}, "CurseLit": {"likely emotion": "submission", "times tested": [13, 9, 11, 18], "pleasentness": -0.36, "attention": -0.52, "sensitivity": -1.96, "aptitude": 1.95}, "ilgabb73": {"likely emotion": "rivalry", "times tested": [1, 1, 1, 1], "pleasentness": 0, "attention": 0, "sensitivity": 0, "aptitude": 0}, "itsjor11RainbowJorja": {"likely emotion": "rivalry", "times tested": [1, 1, 1, 1], "pleasentness": 0, "attention": 0, "sensitivity": 0, "aptitude": 0}, "Kreygasm": {"likely emotion": "frivolity", "times tested": [127, 135, 135, 133], "pleasentness": 100.62, "attention": -53.79, "sensitivity": -50.22, "aptitude": 15.9}, "4Head": {"likely emotion": "contempt", "times tested": [59, 64, 71, 62], "pleasentness": 27.58, "attention": -11.27, "sensitivity": 56.63, "aptitude": -55.4}, "BloodTrail": {"likely emotion": "gloat", "times tested": [97, 118, 106, 105], "pleasentness": 49.46, "attention": -4.15, "sensitivity": -15.05, "aptitude": -7.14}, "SeemsGood": {"likely emotion": "rivalry", "times tested": [54, 40, 27, 53], "pleasentness": 0.46, "attention": -3.72, "sensitivity": 5.85, "aptitude": 3.79}, "bleedPurple": {"likely emotion": "rejection", "times tested": [22, 18, 19, 32], "pleasentness": 3.45, "attention": -4.85, "sensitivity": 4.0, "aptitude": 1.22}, "VoHiYo": {"likely emotion": "love", "times tested": [24, 16, 18, 28], "pleasentness": 3.83, "attention": -2.03, "sensitivity": 2.68, "aptitude": 2.93}, "HeyGuys": {"likely emotion": "rivalry", "times tested": [30, 29, 39, 36], "pleasentness": 4.86, "attention": -1.5, "sensitivity": 8.72, "aptitude": 1.78}, "ResidentSleeper": {"likely emotion": "frivolity", "times tested": [73, 68, 43, 59], "pleasentness": 5.56, "attention": -15.49, "sensitivity": 2.71, "aptitude": 10.15}, "WutFace": {"likely emotion": "anxiety", "times tested": [169, 166, 167, 166], "pleasentness": -1.97, "attention": 121.7, "sensitivity": -119.46, "aptitude": 57.52}, "KappaPride": {"likely emotion": "disapproval", "times tested": [17, 35, 20, 28], "pleasentness": -5.75, "attention": -3.09, "sensitivity": 3.52, "aptitude": 2.67}, "BabyRage": {"likely emotion": "rejection", "times tested": [26, 25, 27, 29], "pleasentness": -3.65, "attention": -20.18, "sensitivity": 20.1, "aptitude": -18.67}, "DansGame": {"likely emotion": "disapproval", "times tested": [129, 122, 117, 128], "pleasentness": -106.76, "attention": -108.72, "sensitivity": 102.96, "aptitude": -51.21}, "lukickSleeper": {"likely emotion": "rivalry", "times tested": [1, 1, 1, 1], "pleasentness": 0, "attention": 0, "sensitivity": 0, "aptitude": 0}, "maskof3Guk": {"likely emotion": "rivalry", "times tested": [1, 1, 1, 1], "pleasentness": 0, "attention": 0, "sensitivity": 0, "aptitude": 0}, "nebelHERZ": {"likely emotion": "rivalry", "times tested": [1, 1, 1, 1], "pleasentness": 0, "attention": 0, "sensitivity": 0, "aptitude": 0}, "nakoGalante": {"likely emotion": "rivalry", "times tested": [1, 1, 1, 1], "pleasentness": 0, "attention": 0, "sensitivity": 0, "aptitude": 0}, "chimichaNga": {"likely emotion": "rivalry", "times tested": [1, 1, 1, 1], "pleasentness": 0, "attention": 0, "sensitivity": 0, "aptitude": 0}, "opcGwawa2": {"likely emotion": "rivalry", "times tested": [1, 1, 1, 1], "pleasentness": 0, "attention": 0, "sensitivity": 0, "aptitude": 0}, "solemChonker": {"likely emotion": "rivalry", "times tested": [1, 1, 1, 1], "pleasentness": 0, "attention": 0, "sensitivity": 0, "aptitude": 0}, "gaminaKappa": {"likely emotion": "rivalry", "times tested": [1, 1, 1, 1], "pleasentness": 0, "attention": 0, "sensitivity": 0, "aptitude": 0}, ":(": {"likely emotion": "frustation", "times tested": [62, 39, 47, 61], "pleasentness": -14.97, "attention": 5.61, "sensitivity": -3.54, "aptitude": -2.05}, "kattah1JAM": {"likely emotion": "rivalry", "times tested": [1, 1, 1, 1], "pleasentness": 0, "attention": 0, "sensitivity": 0, "aptitude": 0}, "uhleeeQueen": {"likely emotion": "rivalry", "times tested": [1, 1, 1, 1], "pleasentness": 0, "attention": 0, "sensitivity": 0, "aptitude": 0}, "s3r4Bund": {"likely emotion": "rivalry", "times tested": [1, 1, 1, 1], "pleasentness": 0, "attention": 0, "sensitivity": 0, "aptitude": 0}, "VoteYea": {"likely emotion": "love", "times tested": [18, 9, 9, 8], "pleasentness": 4.06, "attention": -0.88, "sensitivity": -1.01, "aptitude": 1.82}, "mullLove": {"likely emotion": "rivalry", "times tested": [1, 1, 1, 1], "pleasentness": 0, "attention": 0, "sensitivity": 0, "aptitude": 0}, "kattah1Despair": {"likely emotion": "rivalry", "times tested": [1, 1, 1, 1], "pleasentness": 0, "attention": 0, "sensitivity": 0, "aptitude": 0}, "TombRaid": {"likely emotion": "rivalry", "times tested": [5, 3, 6, 2], "pleasentness": 0.64, "attention": 0.02, "sensitivity": 0.65, "aptitude": 0.3}, "sheydoN": {"likely emotion": "rivalry", "times tested": [1, 1, 1, 1], "pleasentness": 0, "attention": 0, "sensitivity": 0, "aptitude": 0}, "chrisGrin": {"likely emotion": "rivalry", "times tested": [1, 1, 1, 1], "pleasentness": 0, "attention": 0, "sensitivity": 0, "aptitude": 0}, "firneiSMOrc": {"likely emotion": "rivalry", "times tested": [1, 1, 1, 1], "pleasentness": 0, "attention": 0, "sensitivity": 0, "aptitude": 0}, "annytfDinkDonk": {"likely emotion": "love", "times tested": [2, 1, 1, 1], "pleasentness": 0.4, "attention": 0, "sensitivity": 0, "aptitude": 0}, "mxgedFunny": {"likely emotion": "rivalry", "times tested": [1, 1, 1, 1], "pleasentness": 0, "attention": 0, "sensitivity": 0, "aptitude": 0}, "BatChest": {"likely emotion": "frivolity", "times tested": [217, 245, 237, 221], "pleasentness": 142.12, "attention": -123.8, "sensitivity": 110.48, "aptitude": -114.16}, "VirtualHug": {"likely emotion": "love", "times tested": [24, 8, 6, 18], "pleasentness": 1.18, "attention": 1.58, "sensitivity": -0.22, "aptitude": 1.75}, "mitroxNyaa": {"likely emotion": "rivalry", "times tested": [1, 1, 1, 1], "pleasentness": 0, "attention": 0, "sensitivity": 0, "aptitude": 0}, "znakhoGalante": {"likely emotion": "rivalry", "times tested": [1, 1, 1, 1], "pleasentness": 0, "attention": 0, "sensitivity": 0, "aptitude": 0}, "Jebaited": {"likely emotion": "frivolity", "times tested": [67, 59, 66, 65], "pleasentness": 56.58, "attention": -50.16, "sensitivity": 6.49, "aptitude": -12.02}, "MrDestructoid": {"likely emotion": "envy", "times tested": [20, 20, 8, 23], "pleasentness": -3.35, "attention": 0.37, "sensitivity": -3.13, "aptitude": 3.45}, "nebelB": {"likely emotion": "rivalry", "times tested": [1, 1, 1, 1], "pleasentness": 0, "attention": 0, "sensitivity": 0, "aptitude": 0}, "zaludE": {"likely emotion": "rivalry", "times tested": [1, 1, 1, 1], "pleasentness": 0, "attention": 0, "sensitivity": 0, "aptitude": 0}, "Keepo": {"likely emotion": "coercion", "times tested": [3, 1, 4, 3], "pleasentness": 0.15, "attention": 0, "sensitivity": -1.05, "aptitude": -0.48}, "GivePLZ": {"likely emotion": "gloat", "times tested": [8, 6, 9, 9], "pleasentness": 2.84, "attention": -0.06, "sensitivity": 0.43, "aptitude": -2.44}, "pajalW": {"likely emotion": "rivalry", "times tested": [1, 1, 1, 1], "pleasentness": 0, "attention": 0, "sensitivity": 0, "aptitude": 0}, "CoolCat": {"likely emotion": "submission", "times tested": [17, 19, 19, 13], "pleasentness": -1.83, "attention": 0.09, "sensitivity": -14.54, "aptitude": 3.77}, "TwitchUnity": {"likely emotion": "envy", "times tested": [26, 9, 8, 27], "pleasentness": -8.52, "attention": 1.38, "sensitivity": 0.25, "aptitude": 1.72}, "PRChase": {"likely emotion": "envy", "times tested": [4, 3, 1, 5], "pleasentness": -0.91, "attention": 0.49, "sensitivity": 0, "aptitude": 1.7}, "retrora7": {"likely emotion": "rivalry", "times tested": [1, 1, 1, 1], "pleasentness": 0, "attention": 0, "sensitivity": 0, "aptitude": 0}, "forsenT": {"likely emotion": "frustation", "times tested": [3, 3, 14, 5], "pleasentness": -0.76, "attention": 1.22, "sensitivity": 0.6, "aptitude": -0.32}, "SingsNote": {"likely emotion": "disapproval", "times tested": [7, 4, 3, 7], "pleasentness": -2.15, "attention": -1.85, "sensitivity": -0.35, "aptitude": -0.29}, "D3VlD": {"likely emotion": "rivalry", "times tested": [1, 1, 1, 1], "pleasentness": 0, "attention": 0, "sensitivity": 0, "aptitude": 0}, "flushE": {"likely emotion": "gloat", "times tested": [49, 58, 56, 63], "pleasentness": 33.0, "attention": 0.77, "sensitivity": 28.59, "aptitude": -11.46}, "DuckerZ": {"likely emotion": "rejection", "times tested": [10, 10, 11, 11], "pleasentness": 1.31, "attention": -2.79, "sensitivity": 2.6, "aptitude": -0.94}, "D:": {"likely emotion": "disapproval", "times tested": [318, 268, 290, 280], "pleasentness": -246.17, "attention": -217.29, "sensitivity": 123.45, "aptitude": 3.25}, "NaM": {"likely emotion": "rivalry", "times tested": [10, 9, 13, 14], "pleasentness": 0.2, "attention": -0.56, "sensitivity": 3.26, "aptitude": 5.07}, "JUMP": {"likely emotion": "rejection", "times tested": [10, 13, 7, 12], "pleasentness": -1.2, "attention": -4.03, "sensitivity": 1.62, "aptitude": 2.36}, "ZULUL": {"likely emotion": "frustation", "times tested": [87, 63, 56, 37], "pleasentness": -61.73, "attention": 23.05, "sensitivity": 10.13, "aptitude": -9.99}, "FireSpeed": {"likely emotion": "envy", "times tested": [2, 3, 2, 2], "pleasentness": -0.6, "attention": 0.52, "sensitivity": -0.41, "aptitude": 0.84}, "PalDouble": {"likely emotion": "rivalry", "times tested": [1, 1, 1, 1], "pleasentness": 0, "attention": 0, "sensitivity": 0, "aptitude": 0}, "purpleCx": {"likely emotion": "rivalry", "times tested": [1, 1, 1, 1], "pleasentness": 0, "attention": 0, "sensitivity": 0, "aptitude": 0}, "TRUEING": {"likely emotion": "optimism", "times tested": [10, 10, 5, 6], "pleasentness": 4.28, "attention": 7.33, "sensitivity": 1.46, "aptitude": 0.24}, "AxelBased": {"likely emotion": "rivalry", "times tested": [1, 1, 1, 1], "pleasentness": 0, "attention": 0, "sensitivity": 0, "aptitude": 0}, "Clap": {"likely emotion": "love", "times tested": [187, 184, 187, 232], "pleasentness": 73.41, "attention": -73.29, "sensitivity": -52.6, "aptitude": 87.14}, "catJAM": {"likely emotion": "rivalry", "times tested": [60, 83, 125, 144], "pleasentness": 29.51, "attention": -2.52, "sensitivity": 39.52, "aptitude": 28.44}, "iamsocal": {"likely emotion": "rivalry", "times tested": [1, 1, 1, 1], "pleasentness": 0, "attention": 0, "sensitivity": 0, "aptitude": 0}, "sillyTiz": {"likely emotion": "rivalry", "times tested": [1, 1, 1, 1], "pleasentness": 0, "attention": 0, "sensitivity": 0, "aptitude": 0}, "blobDance": {"likely emotion": "love", "times tested": [11, 9, 13, 7], "pleasentness": 3.46, "attention": -0.57, "sensitivity": -0.1, "aptitude": 0.57}, "Trikose": {"likely emotion": "rivalry", "times tested": [1, 1, 1, 1], "pleasentness": 0, "attention": 0, "sensitivity": 0, "aptitude": 0}, "eeveeDance": {"likely emotion": "rivalry", "times tested": [1, 1, 1, 1], "pleasentness": 0, "attention": 0, "sensitivity": 0, "aptitude": 0}, "Pogpega": {"likely emotion": "rivalry", "times tested": [1, 1, 1, 1], "pleasentness": 0, "attention": 0, "sensitivity": 0, "aptitude": 0}, "FeelsGoodMan": {"likely emotion": "love", "times tested": [118, 110, 108, 116], "pleasentness": 105.75, "attention": 2.32, "sensitivity": -52.53, "aptitude": 12.33}, "zeroSquare": {"likely emotion": "rivalry", "times tested": [1, 1, 1, 1], "pleasentness": 0, "attention": 0, "sensitivity": 0, "aptitude": 0}, "sanaSnuggle": {"likely emotion": "rivalry", "times tested": [1, 1, 1, 1], "pleasentness": 0, "attention": 0, "sensitivity": 0, "aptitude": 0}, "LUCA": {"likely emotion": "coercion", "times tested": [1, 2, 3, 2], "pleasentness": 0, "attention": 0.32, "sensitivity": -0.71, "aptitude": -0.65}, "pepeD": {"likely emotion": "rejection", "times tested": [8, 3, 13, 17], "pleasentness": -0.89, "attention": -0.69, "sensitivity": 5.56, "aptitude": 0.67}, "LuL": {"likely emotion": "love", "times tested": [27, 38, 29, 40], "pleasentness": 4.7, "attention": -0.36, "sensitivity": 4.51, "aptitude": 5.88}, "OMEGALUL": {"likely emotion": "gloat", "times tested": [1511, 1509, 1514, 1504], "pleasentness": 1285.57, "attention": 168.92, "sensitivity": -96.88, "aptitude": -1182.79}, "dnyPls": {"likely emotion": "rivalry", "times tested": [1, 1, 1, 1], "pleasentness": 0, "attention": 0, "sensitivity": 0, "aptitude": 0}, "FeelsBadMan": {"likely emotion": "remorse", "times tested": [80, 82, 82, 78], "pleasentness": -64.72, "attention": -2.48, "sensitivity": -10.3, "aptitude": -51.39}, "monkaS": {"likely emotion": "anxiety", "times tested": [159, 145, 141, 131], "pleasentness": 1.18, "attention": 114.36, "sensitivity": -113.27, "aptitude": 0.84}, "gachiBASS": {"likely emotion": "optimism", "times tested": [18, 7, 9, 22], "pleasentness": 5.79, "attention": 1.98, "sensitivity": 0.71, "aptitude": 1.73}, "EZ": {"likely emotion": "anxiety", "times tested": [402, 341, 357, 459], "pleasentness": 118.98, "attention": 209.81, "sensitivity": -241.68, "aptitude": 117.66}, "Kanyewheat": {"likely emotion": "rivalry", "times tested": [1, 1, 1, 1], "pleasentness": 0, "attention": 0, "sensitivity": 0, "aptitude": 0}, "sumParrot": {"likely emotion": "rivalry", "times tested": [1, 1, 1, 1], "pleasentness": 0, "attention": 0, "sensitivity": 0, "aptitude": 0}, "haHAA": {"likely emotion": "contempt", "times tested": [136, 120, 114, 144], "pleasentness": 19.03, "attention": -51.48, "sensitivity": 97.18, "aptitude": -118.14}, "4Weirding": {"likely emotion": "rivalry", "times tested": [1, 1, 1, 1], "pleasentness": 0, "attention": 0, "sensitivity": 0, "aptitude": 0}, "lucaKuk": {"likely emotion": "rivalry", "times tested": [1, 1, 1, 1], "pleasentness": 0, "attention": 0, "sensitivity": 0, "aptitude": 0}, "Primi": {"likely emotion": "rivalry", "times tested": [1, 1, 1, 1], "pleasentness": 0, "attention": 0, "sensitivity": 0, "aptitude": 0}, "SourPls": {"likely emotion": "optimism", "times tested": [6, 3, 1, 4], "pleasentness": 3.84, "attention": 0.09, "sensitivity": 0, "aptitude": 0.07}, "kiandoAYAYA": {"likely emotion": "rivalry", "times tested": [1, 1, 1, 1], "pleasentness": 0, "attention": 0, "sensitivity": 0, "aptitude": 0}, "KEKW": {"likely emotion": "gloat", "times tested": [1066, 1074, 1140, 1150], "pleasentness": 719.28, "attention": 159.38, "sensitivity": 176.14, "aptitude": -717.32}, "TriKool": {"likely emotion": "love", "times tested": [13, 4, 9, 8], "pleasentness": 2.57, "attention": -1.02, "sensitivity": -0.07, "aptitude": 1.61}, "pepeJAM": {"likely emotion": "envy", "times tested": [13, 6, 9, 14], "pleasentness": -5.39, "attention": -0.72, "sensitivity": 3.43, "aptitude": 3.25}, "TriDance": {"likely emotion": "rivalry", "times tested": [18, 10, 12, 23], "pleasentness": 1.79, "attention": 0.8, "sensitivity": 2.18, "aptitude": 2.29}, "Dance": {"likely emotion": "submission", "times tested": [4, 6, 10, 7], "pleasentness": -0.32, "attention": 0.1, "sensitivity": -1.24, "aptitude": 0.45}, "AYAYA": {"likely emotion": "envy", "times tested": [40, 19, 15, 32], "pleasentness": -8.31, "attention": 3.4, "sensitivity": -0.78, "aptitude": 10.03}, "ppOverheat": {"likely emotion": "optimism", "times tested": [6, 2, 3, 7], "pleasentness": 2.77, "attention": 0.19, "sensitivity": 0.17, "aptitude": 0.02}, "papajOk": {"likely emotion": "rivalry", "times tested": [1, 1, 1, 1], "pleasentness": 0, "attention": 0, "sensitivity": 0, "aptitude": 0}, "pepeDS": {"likely emotion": "frustation", "times tested": [2, 2, 1, 3], "pleasentness": -0.96, "attention": 0.22, "sensitivity": 0, "aptitude": -0.01}, "KEKWait": {"likely emotion": "anxiety", "times tested": [9, 4, 11, 17], "pleasentness": 0.18, "attention": 1.38, "sensitivity": -2.31, "aptitude": -0.86}, "RainbowPls": {"likely emotion": "submission", "times tested": [4, 1, 4, 1], "pleasentness": 0.01, "attention": 0, "sensitivity": -1.26, "aptitude": 0}, "gachiHYPER": {"likely emotion": "love", "times tested": [27, 14, 29, 26], "pleasentness": 3.59, "attention": -1.56, "sensitivity": 1.58, "aptitude": 9.79}, "PepePls": {"likely emotion": "frustation", "times tested": [6, 3, 1, 4], "pleasentness": -2.73, "attention": 0.94, "sensitivity": 0, "aptitude": 0.71}, "xar2EDM": {"likely emotion": "rejection", "times tested": [1, 2, 1, 3], "pleasentness": 0, "attention": -0.51, "sensitivity": 0, "aptitude": -0.12}, "POGGERS": {"likely emotion": "love", "times tested": [17, 31, 24, 37], "pleasentness": 4.93, "attention": -13.66, "sensitivity": 1.71, "aptitude": 18.6}, "AlienPls": {"likely emotion": "rejection", "times tested": [60, 80, 52, 35], "pleasentness": -21.62, "attention": -9.26, "sensitivity": 31.0, "aptitude": -1.3}, "faisterMoin": {"likely emotion": "rivalry", "times tested": [1, 1, 1, 1], "pleasentness": 0, "attention": 0, "sensitivity": 0, "aptitude": 0}, "HYPERCLAP": {"likely emotion": "frivolity", "times tested": [2, 5, 3, 2], "pleasentness": 0.71, "attention": -3.04, "sensitivity": 0.07, "aptitude": 0.07}, "ppppporcoDio": {"likely emotion": "rivalry", "times tested": [1, 1, 1, 1], "pleasentness": 0, "attention": 0, "sensitivity": 0, "aptitude": 0}, "pokiJAM": {"likely emotion": "rivalry", "times tested": [1, 1, 1, 1], "pleasentness": 0, "attention": 0, "sensitivity": 0, "aptitude": 0}, "pugPls": {"likely emotion": "contempt", "times tested": [7, 1, 8, 8], "pleasentness": 1.92, "attention": 0, "sensitivity": 3.55, "aptitude": -0.16}, "PartyParrot": {"likely emotion": "love", "times tested": [7, 3, 2, 5], "pleasentness": 1.93, "attention": -0.05, "sensitivity": 0.01, "aptitude": 2.11}, "PartyKirby": {"likely emotion": "rivalry", "times tested": [1, 1, 1, 1], "pleasentness": 0, "attention": 0, "sensitivity": 0, "aptitude": 0}, "ricardoFlick": {"likely emotion": "rivalry", "times tested": [1, 1, 1, 1], "pleasentness": 0, "attention": 0, "sensitivity": 0, "aptitude": 0}, "AISmug": {"likely emotion": "rivalry", "times tested": [1, 1, 1, 1], "pleasentness": 0, "attention": 0, "sensitivity": 0, "aptitude": 0}, "Goob": {"likely emotion": "rivalry", "times tested": [1, 1, 1, 1], "pleasentness": 0, "attention": 0, "sensitivity": 0, "aptitude": 0}, "PEPEDS": {"likely emotion": "rivalry", "times tested": [1, 1, 1, 1], "pleasentness": 0, "attention": 0, "sensitivity": 0, "aptitude": 0}, "quintPls": {"likely emotion": "rivalry", "times tested": [1, 1, 1, 1], "pleasentness": 0, "attention": 0, "sensitivity": 0, "aptitude": 0}, "Sadge": {"likely emotion": "remorse", "times tested": [284, 260, 278, 277], "pleasentness": -224.41, "attention": -1.64, "sensitivity": 4.26, "aptitude": -212.49}, "dvdSimp": {"likely emotion": "rivalry", "times tested": [1, 1, 1, 1], "pleasentness": 0, "attention": 0, "sensitivity": 0, "aptitude": 0}, "TeaTime": {"likely emotion": "gloat", "times tested": [419, 367, 427, 443], "pleasentness": 106.11, "attention": -10.69, "sensitivity": -47.5, "aptitude": -35.51}, "KKona": {"likely emotion": "awe", "times tested": [49, 41, 37, 43], "pleasentness": 4.91, "attention": -2.93, "sensitivity": -7.74, "aptitude": 2.77}, "gachiGASM": {"likely emotion": "envy", "times tested": [3, 10, 5, 11], "pleasentness": -1.04, "attention": -2.01, "sensitivity": 0.66, "aptitude": 2.87}, "PepoDance": {"likely emotion": "gloat", "times tested": [2, 2, 2, 3], "pleasentness": 0.58, "attention": 0.22, "sensitivity": 0.57, "aptitude": -0.84}, ":tf:": {"likely emotion": "contempt", "times tested": [56, 36, 46, 37], "pleasentness": -0.03, "attention": 4.51, "sensitivity": 3.38, "aptitude": -22.86}, "PogU": {"likely emotion": "love", "times tested": [85, 69, 67, 101], "pleasentness": 21.65, "attention": -27.84, "sensitivity": -15.42, "aptitude": 40.1}, "peepoClap": {"likely emotion": "optimism", "times tested": [2, 2, 4, 1], "pleasentness": 1.04, "attention": 0.26, "sensitivity": 0.0, "aptitude": 0}, "ppJedi": {"likely emotion": "rivalry", "times tested": [1, 1, 1, 1], "pleasentness": 0, "attention": 0, "sensitivity": 0, "aptitude": 0}, "BelloWeird": {"likely emotion": "rivalry", "times tested": [1, 1, 1, 1], "pleasentness": 0, "attention": 0, "sensitivity": 0, "aptitude": 0}, "WAYTOODANK": {"likely emotion": "disapproval", "times tested": [248, 237, 228, 245], "pleasentness": -205.57, "attention": -206.84, "sensitivity": 193.91, "aptitude": -0.02}, "PepeLaugh": {"likely emotion": "gloat", "times tested": [178, 165, 173, 176], "pleasentness": 70.31, "attention": 29.25, "sensitivity": 18.99, "aptitude": -42.15}, "PepeHands": {"likely emotion": "remorse", "times tested": [142, 78, 114, 121], "pleasentness": -75.64, "attention": 2.06, "sensitivity": -6.96, "aptitude": -47.1}, "NODDERS": {"likely emotion": "envy", "times tested": [83, 52, 66, 74], "pleasentness": -31.01, "attention": -1.95, "sensitivity": -4.67, "aptitude": 14.94}, "ratJAM": {"likely emotion": "disapproval", "times tested": [11, 9, 8, 6], "pleasentness": -5.63, "attention": -2.21, "sensitivity": -1.42, "aptitude": 0.78}, "headBang": {"likely emotion": "rejection", "times tested": [8, 6, 5, 6], "pleasentness": 0.01, "attention": -1.19, "sensitivity": 0.6, "aptitude": 0.45}, "DharMannBowser": {"likely emotion": "rivalry", "times tested": [1, 1, 1, 1], "pleasentness": 0, "attention": 0, "sensitivity": 0, "aptitude": 0}, "DuckerPls": {"likely emotion": "rivalry", "times tested": [1, 1, 1, 1], "pleasentness": 0, "attention": 0, "sensitivity": 0, "aptitude": 0}, "allanKKonaW": {"likely emotion": "rivalry", "times tested": [1, 1, 1, 1], "pleasentness": 0, "attention": 0, "sensitivity": 0, "aptitude": 0}, "kattahDuck": {"likely emotion": "rivalry", "times tested": [1, 1, 1, 1], "pleasentness": 0, "attention": 0, "sensitivity": 0, "aptitude": 0}, "GachiPls": {"likely emotion": "frivolity", "times tested": [88, 78, 81, 74], "pleasentness": 22.22, "attention": -22.83, "sensitivity": 6.65, "aptitude": -0.53}, "modCheck": {"likely emotion": "envy", "times tested": [77, 55, 49, 76], "pleasentness": -24.16, "attention": -2.4, "sensitivity": -1.3, "aptitude": 13.47}, "pepeJAMJAM": {"likely emotion": "rivalry", "times tested": [1, 1, 1, 2], "pleasentness": 0, "attention": 0, "sensitivity": 0, "aptitude": 0.59}, "GuitarTime": {"likely emotion": "awe", "times tested": [59, 63, 43, 47], "pleasentness": 5.49, "attention": -19.93, "sensitivity": -7.37, "aptitude": 8.45}, "PepoCheer": {"likely emotion": "rivalry", "times tested": [1, 1, 1, 1], "pleasentness": 0, "attention": 0, "sensitivity": 0, "aptitude": 0}, "zyzzRave": {"likely emotion": "rivalry", "times tested": [1, 1, 1, 1], "pleasentness": 0, "attention": 0, "sensitivity": 0, "aptitude": 0}, "forsenDiscoSnake": {"likely emotion": "love", "times tested": [115, 64, 35, 248], "pleasentness": 28.15, "attention": -9.09, "sensitivity": 19.57, "aptitude": 11.74}, "CrabPls": {"likely emotion": "rivalry", "times tested": [1, 1, 1, 1], "pleasentness": 0, "attention": 0, "sensitivity": 0, "aptitude": 0}, "HyeImShy": {"likely emotion": "rivalry", "times tested": [1, 1, 1, 1], "pleasentness": 0, "attention": 0, "sensitivity": 0, "aptitude": 0}, "No1": {"likely emotion": "rivalry", "times tested": [1, 1, 2, 1], "pleasentness": 0, "attention": 0, "sensitivity": 0.12, "aptitude": 0}, "DNAFlamingo": {"likely emotion": "rivalry", "times tested": [1, 1, 1, 1], "pleasentness": 0, "attention": 0, "sensitivity": 0, "aptitude": 0}, "CHILLS": {"likely emotion": "gloat", "times tested": [33, 14, 29, 41], "pleasentness": 10.25, "attention": -0.9, "sensitivity": -0.84, "aptitude": -2.12}, "MarkZynk": {"likely emotion": "rivalry", "times tested": [1, 1, 1, 1], "pleasentness": 0, "attention": 0, "sensitivity": 0, "aptitude": 0}, "YEP": {"likely emotion": "frustation", "times tested": [36, 24, 23, 19], "pleasentness": -29.36, "attention": 13.0, "sensitivity": 9.54, "aptitude": 4.5}, "BORT": {"likely emotion": "rejection", "times tested": [4, 9, 4, 4], "pleasentness": 0.78, "attention": -1.93, "sensitivity": 1.02, "aptitude": 1.06}, "EnzoWideHardo": {"likely emotion": "rivalry", "times tested": [1, 1, 1, 1], "pleasentness": 0, "attention": 0, "sensitivity": 0, "aptitude": 0}, "WideHardo": {"likely emotion": "rivalry", "times tested": [12, 9, 10, 21], "pleasentness": 0.64, "attention": -0.6, "sensitivity": 0.83, "aptitude": 8.68}, "bobolSpecial": {"likely emotion": "rivalry", "times tested": [1, 1, 1, 1], "pleasentness": 0, "attention": 0, "sensitivity": 0, "aptitude": 0}, "TriGold": {"likely emotion": "rivalry", "times tested": [1, 1, 1, 1], "pleasentness": 0, "attention": 0, "sensitivity": 0, "aptitude": 0}, "TheMercy15": {"likely emotion": "rivalry", "times tested": [1, 1, 1, 1], "pleasentness": 0, "attention": 0, "sensitivity": 0, "aptitude": 0}, "GetItOut": {"likely emotion": "rivalry", "times tested": [1, 1, 1, 1], "pleasentness": 0, "attention": 0, "sensitivity": 0, "aptitude": 0}, "LULW": {"likely emotion": "gloat", "times tested": [638, 501, 514, 675], "pleasentness": 185.12, "attention": -6.53, "sensitivity": -4.42, "aptitude": -115.73}, "Pog": {"likely emotion": "awe", "times tested": [671, 613, 649, 722], "pleasentness": 285.77, "attention": -530.42, "sensitivity": -548.56, "aptitude": 325.59}, "perSMS": {"likely emotion": "rivalry", "times tested": [1, 1, 1, 1], "pleasentness": 0, "attention": 0, "sensitivity": 0, "aptitude": 0}, "unIukky13": {"likely emotion": "rivalry", "times tested": [1, 1, 1, 1], "pleasentness": 0, "attention": 0, "sensitivity": 0, "aptitude": 0}, "HorstChamp": {"likely emotion": "rivalry", "times tested": [1, 1, 1, 1], "pleasentness": 0, "attention": 0, "sensitivity": 0, "aptitude": 0}, "pepeL": {"likely emotion": "love", "times tested": [6, 9, 6, 6], "pleasentness": 0.94, "attention": 0.61, "sensitivity": 0.74, "aptitude": 2.51}, "DamnWart": {"likely emotion": "rivalry", "times tested": [1, 1, 1, 1], "pleasentness": 0, "attention": 0, "sensitivity": 0, "aptitude": 0}, "pepegeDank": {"likely emotion": "rivalry", "times tested": [1, 1, 1, 1], "pleasentness": 0, "attention": 0, "sensitivity": 0, "aptitude": 0}, "TeaGroup": {"likely emotion": "rivalry", "times tested": [1, 1, 1, 1], "pleasentness": 0, "attention": 0, "sensitivity": 0, "aptitude": 0}, "4Weird": {"likely emotion": "frivolity", "times tested": [4, 6, 3, 1], "pleasentness": 2.46, "attention": -0.38, "sensitivity": -0.79, "aptitude": 0}, "monkaW": {"likely emotion": "anxiety", "times tested": [188, 160, 145, 197], "pleasentness": 15.29, "attention": 114.55, "sensitivity": -71.2, "aptitude": 7.85}, "02Stare": {"likely emotion": "rivalry", "times tested": [1, 1, 1, 1], "pleasentness": 0, "attention": 0, "sensitivity": 0, "aptitude": 0}, "KonanKonznJizzManGuzmanHard": {"likely emotion": "rivalry", "times tested": [1, 1, 1, 1], "pleasentness": 0, "attention": 0, "sensitivity": 0, "aptitude": 0}, "Pepega": {"likely emotion": "aggressiveness", "times tested": [92, 110, 130, 98], "pleasentness": 28.48, "attention": 22.16, "sensitivity": 47.93, "aptitude": 20.77}, "WeirdChamp": {"likely emotion": "disapproval", "times tested": [85, 71, 55, 67], "pleasentness": -16.43, "attention": -10.6, "sensitivity": 6.56, "aptitude": 0.5}, "widepeepoHappy": {"likely emotion": "love", "times tested": [90, 83, 93, 113], "pleasentness": 14.43, "attention": 4.22, "sensitivity": 7.21, "aptitude": 5.94}, "XQC": {"likely emotion": "anxiety", "times tested": [7, 5, 4, 4], "pleasentness": -0.23, "attention": 0.47, "sensitivity": -0.38, "aptitude": 0.39}, "LETSPEPE": {"likely emotion": "rivalry", "times tested": [1, 1, 1, 1], "pleasentness": 0, "attention": 0, "sensitivity": 0, "aptitude": 0}, "SchlonstionTtv": {"likely emotion": "rivalry", "times tested": [1, 1, 1, 1], "pleasentness": 0, "attention": 0, "sensitivity": 0, "aptitude": 0}, "HandsUp": {"likely emotion": "contempt", "times tested": [8, 4, 4, 4], "pleasentness": -0.7, "attention": 0.76, "sensitivity": 1.12, "aptitude": -2.08}, "PagMan": {"likely emotion": "awe", "times tested": [254, 198, 214, 254], "pleasentness": 66.94, "attention": -82.16, "sensitivity": -81.64, "aptitude": 32.46}, "FeelsButtsMan": {"likely emotion": "rivalry", "times tested": [1, 1, 1, 1], "pleasentness": 0, "attention": 0, "sensitivity": 0, "aptitude": 0}, "PagChomp": {"likely emotion": "awe", "times tested": [122, 111, 116, 122], "pleasentness": 33.46, "attention": -55.13, "sensitivity": -56.56, "aptitude": 5.54}, "Kapp": {"likely emotion": "frivolity", "times tested": [57, 60, 64, 64], "pleasentness": 51.28, "attention": -58.23, "sensitivity": -0.55, "aptitude": 1.59}, "forsenCD": {"likely emotion": "disapproval", "times tested": [325, 207, 160, 257], "pleasentness": -163.41, "attention": -40.57, "sensitivity": -16.19, "aptitude": 27.27}, "5Head": {"likely emotion": "frivolity", "times tested": [25, 39, 20, 57], "pleasentness": 11.06, "attention": -21.6, "sensitivity": -4.61, "aptitude": 9.09}, "KEKL": {"likely emotion": "gloat", "times tested": [47, 31, 62, 27], "pleasentness": 24.89, "attention": 2.26, "sensitivity": 11.35, "aptitude": -10.27}, "widepeepoSad": {"likely emotion": "remorse", "times tested": [5, 2, 3, 4], "pleasentness": -2.57, "attention": 0.37, "sensitivity": -1.05, "aptitude": -0.4}, "LOLW": {"likely emotion": "gloat", "times tested": [8, 3, 11, 16], "pleasentness": 4.25, "attention": -0.72, "sensitivity": -1.25, "aptitude": -8.56}, "MaN": {"likely emotion": "envy", "times tested": [28, 10, 13, 22], "pleasentness": -10.1, "attention": 2.51, "sensitivity": -0.71, "aptitude": 5.17}, "WideHard": {"likely emotion": "contempt", "times tested": [7, 4, 7, 11], "pleasentness": 0.03, "attention": -0.93, "sensitivity": 0.82, "aptitude": -2.75}, "DICKS": {"likely emotion": "submission", "times tested": [2, 1, 2, 4], "pleasentness": -0.19, "attention": 0.0, "sensitivity": -0.65, "aptitude": 0.34}, "pepeLaugh": {"likely emotion": "gloat", "times tested": [233, 246, 252, 275], "pleasentness": 54.68, "attention": 3.71, "sensitivity": -22.25, "aptitude": -30.58}, "FeelsOkayMan": {"likely emotion": "envy", "times tested": [90, 82, 83, 90], "pleasentness": -7.46, "attention": -3.52, "sensitivity": -6.36, "aptitude": 23.97}, "Okayge": {"likely emotion": "gloat", "times tested": [45, 31, 34, 28], "pleasentness": 6.39, "attention": -0.25, "sensitivity": -0.02, "aptitude": -3.5}, "FeelsStrongMan": {"likely emotion": "frivolity", "times tested": [66, 47, 57, 69], "pleasentness": 12.14, "attention": -17.67, "sensitivity": -4.7, "aptitude": 15.93}, "PauseChamp": {"likely emotion": "love", "times tested": [27, 21, 26, 37], "pleasentness": 2.99, "attention": 3.17, "sensitivity": -2.8, "aptitude": 6.98}, "FeelsDankMan": {"likely emotion": "gloat", "times tested": [36, 27, 37, 28], "pleasentness": 7.93, "attention": 2.75, "sensitivity": 5.2, "aptitude": -3.9}, "BNASIT": {"likely emotion": "rivalry", "times tested": [1, 1, 1, 1], "pleasentness": 0, "attention": 0, "sensitivity": 0, "aptitude": 0}, "KKonaW": {"likely emotion": "rejection", "times tested": [36, 37, 29, 29], "pleasentness": 0.7, "attention": -15.38, "sensitivity": 5.26, "aptitude": 4.55}, "3Head": {"likely emotion": "submission", "times tested": [17, 12, 15, 23], "pleasentness": 1.29, "attention": -8.65, "sensitivity": -1.44, "aptitude": 9.63}, "WTFF": {"likely emotion": "frivolity", "times tested": [3, 4, 1, 2], "pleasentness": 0.27, "attention": -0.92, "sensitivity": 0, "aptitude": -0.25}, "WICKED": {"likely emotion": "love", "times tested": [10, 17, 11, 36], "pleasentness": 4.06, "attention": -1.67, "sensitivity": 0.95, "aptitude": 24.29}, "PogO": {"likely emotion": "envy", "times tested": [110, 56, 60, 103], "pleasentness": -17.64, "attention": -6.95, "sensitivity": -4.44, "aptitude": 48.69}, "pepeW": {"likely emotion": "contempt", "times tested": [3, 3, 3, 5], "pleasentness": 0.32, "attention": 0.53, "sensitivity": 0.49, "aptitude": -0.94}, "monkaOMEGA": {"likely emotion": "anxiety", "times tested": [85, 96, 70, 57], "pleasentness": -22.9, "attention": 40.3, "sensitivity": -23.42, "aptitude": 29.79}, "peepoHappy": {"likely emotion": "rivalry", "times tested": [11, 14, 19, 17], "pleasentness": 1.18, "attention": 1.92, "sensitivity": 2.2, "aptitude": 9.5}, "PepeScoots": {"likely emotion": "rivalry", "times tested": [1, 1, 1, 1], "pleasentness": 0, "attention": 0, "sensitivity": 0, "aptitude": 0}, "WeebsOut": {"likely emotion": "rivalry", "times tested": [1, 1, 1, 1], "pleasentness": 0, "attention": 0, "sensitivity": 0, "aptitude": 0}, "HYPERS": {"likely emotion": "aggressiveness", "times tested": [4, 2, 4, 1], "pleasentness": 0.67, "attention": 0.76, "sensitivity": 0.75, "aptitude": 0}, "FeelsSpecialMan": {"likely emotion": "rivalry", "times tested": [1, 1, 2, 1], "pleasentness": 0, "attention": 0, "sensitivity": 0.41, "aptitude": 0}, "REEeee": {"likely emotion": "rivalry", "times tested": [1, 1, 1, 1], "pleasentness": 0, "attention": 0, "sensitivity": 0, "aptitude": 0}, "monkaT": {"likely emotion": "rivalry", "times tested": [1, 1, 1, 1], "pleasentness": 0, "attention": 0, "sensitivity": 0, "aptitude": 0}, "SadPepe": {"likely emotion": "rivalry", "times tested": [1, 1, 1, 1], "pleasentness": 0, "attention": 0, "sensitivity": 0, "aptitude": 0}, "YuuBooty": {"likely emotion": "rivalry", "times tested": [1, 1, 1, 1], "pleasentness": 0, "attention": 0, "sensitivity": 0, "aptitude": 0}, "AYAYAHyper": {"likely emotion": "rivalry", "times tested": [1, 1, 1, 1], "pleasentness": 0, "attention": 0, "sensitivity": 0, "aptitude": 0}, "peepoLove": {"likely emotion": "love", "times tested": [20, 8, 12, 23], "pleasentness": 6.42, "attention": -0.39, "sensitivity": 0.31, "aptitude": 7.48}, "Prayge": {"likely emotion": "envy", "times tested": [47, 47, 26, 58], "pleasentness": -2.84, "attention": -4.55, "sensitivity": -0.24, "aptitude": 22.92}, "Weirdga": {"likely emotion": "rivalry", "times tested": [1, 1, 1, 1], "pleasentness": 0, "attention": 0, "sensitivity": 0, "aptitude": 0}, "PepeSuspicious": {"likely emotion": "rivalry", "times tested": [1, 1, 1, 1], "pleasentness": 0, "attention": 0, "sensitivity": 0, "aptitude": 0}, "monkaHmm": {"likely emotion": "envy", "times tested": [20, 17, 13, 14], "pleasentness": -3.22, "attention": -0.41, "sensitivity": -1.52, "aptitude": 3.14}, "FeelsNotsureMan": {"likely emotion": "rivalry", "times tested": [1, 1, 1, 1], "pleasentness": 0, "attention": 0, "sensitivity": 0, "aptitude": 0}, "Dolan": {"likely emotion": "rivalry", "times tested": [1, 1, 1, 1], "pleasentness": 0, "attention": 0, "sensitivity": 0, "aptitude": 0}, "EZZ": {"likely emotion": "submission", "times tested": [2, 1, 4, 1], "pleasentness": 0.1, "attention": 0, "sensitivity": -2.91, "aptitude": 0}, "DougDimmadomeOwnerOfTheDimmsdaleDimmadomeLookingOutHisDimmsdaleDimmadomeLookingOutSpongebobsWindowAndKnucklesFtDanteDOIT": {"likely emotion": "rivalry", "times tested": [1, 1, 1, 1], "pleasentness": 0, "attention": 0, "sensitivity": 0, "aptitude": 0}, "FeelsWeirdMan": {"likely emotion": "disapproval", "times tested": [14, 14, 11, 13], "pleasentness": -4.08, "attention": -2.02, "sensitivity": 1.42, "aptitude": 1.44}, "OLEDOIT": {"likely emotion": "rivalry", "times tested": [1, 1, 1, 1], "pleasentness": 0, "attention": 0, "sensitivity": 0, "aptitude": 0}, "forsenParty": {"likely emotion": "rivalry", "times tested": [22, 21, 22, 23], "pleasentness": -2.04, "attention": 0.13, "sensitivity": 6.45, "aptitude": 0.14}}